Metadata-Version: 2.1
Name: free-storage
Version: 0.1.0
Summary: Accessing GoogleDrive as if it is your local drive
Home-page: UNKNOWN
Author: Jeffrey Tang
License: MIT
Platform: UNKNOWN
Classifier: License :: OSI Approved :: MIT License
Classifier: Programming Language :: Python
Classifier: Programming Language :: Python :: 3
Classifier: Programming Language :: Python :: 3.6
Classifier: Programming Language :: Python :: Implementation :: CPython
Classifier: Programming Language :: Python :: Implementation :: PyPy
Requires-Python: >=3.5.0
